fycharts/SpotifyCharts.py
fycharts/__init__.py
fycharts/cli.py
fycharts/compute_dates.py
fycharts/crawler_base.py
fycharts/exceptions.py
fycharts/log_config.py
fycharts/write_to_outputs.py
fycharts-4.0.2.dist-info/LICENSE
fycharts-4.0.2.dist-info/METADATA
fycharts-4.0.2.dist-info/WHEEL
fycharts-4.0.2.dist-info/entry_points.txt
fycharts-4.0.2.dist-info/top_level.txt
fycharts-4.0.2.dist-info/RECORD
