Metadata-Version: 2.1
Name: fycharts
Version: 4.0.2
Summary: A fully-fledged installable python package for extracting top 200 and viral 50 charts off of spotifycharts.com
Home-page: https://github.com/kelvingakuo/fycharts
Author: Kelvin Gakuo
Author-email: kelvingakuo@gmail.com
License: UNKNOWN
Platform: UNKNOWN
Classifier: Programming Language :: Python :: 3.5
Classifier: License :: OSI Approved :: MIT License
Classifier: Operating System :: OS Independent
Requires-Dist: pandas (==1.1.2)
Requires-Dist: requests (==2.24.0)
Requires-Dist: click (==7.1.2)
Requires-Dist: colorama (==0.4.3)
